test_pypi_package_toby/__init__.py
test_pypi_package_toby/example.py
test_pypi_package_toby-0.1.0.dist-info/METADATA
test_pypi_package_toby-0.1.0.dist-info/WHEEL
test_pypi_package_toby-0.1.0.dist-info/RECORD
