Metadata-Version: 2.1
Name: test-pypi-package-toby
Version: 0.1.0
Summary: test pypi publish
Author: caochaowu
Author-email: caochaowu@163.com
Requires-Python: >=3.11,<4.0
Classifier: Programming Language :: Python :: 3
Classifier: Programming Language :: Python :: 3.11
Classifier: Programming Language :: Python :: 3.12
Classifier: Programming Language :: Python :: 3.13
